setup.py
yandex_xml_parser/__init__.py
yandex_xml_parser/exceptions.py
yandex_xml_parser.egg-info/PKG-INFO
yandex_xml_parser.egg-info/SOURCES.txt
yandex_xml_parser.egg-info/dependency_links.txt
yandex_xml_parser.egg-info/top_level.txt