Metadata-Version: 1.1
Name: yandex-xml-parser
Version: 0.0.9
Summary: Yandex xml parser
Home-page: https://github.com/KokocGroup/yandex-xml-parser
Author: UNKNOWN
Author-email: UNKNOWN
License: UNKNOWN
Download-URL: https://github.com/KokocGroup/yandex-xml-parser/tarball/v0.0.9
Platform: UNKNOWN
